yacs/__init__.py
yacs/cli.py
yacs/get.py
yacs/inititialize.py
yacs/put.py
yacs/reset.py
yacs/util.py
yacs/view.py
yacs_cli-0.1.0.dist-info/LICENSE
yacs_cli-0.1.0.dist-info/METADATA
yacs_cli-0.1.0.dist-info/WHEEL
yacs_cli-0.1.0.dist-info/entry_points.txt
yacs_cli-0.1.0.dist-info/top_level.txt
yacs_cli-0.1.0.dist-info/RECORD
