Metadata-Version: 2.1
Name: yacs-cli
Version: 0.1.0
Summary: Run a local credential store.
Home-page: https://github.com/raiyanyahya/yacs
Author: Raiyan Yahya
Author-email: raiyanyahyadeveloper@gmail.com
License: MIT
Keywords: cli,developer tools,productivity,tools,secretsmanager
Platform: UNKNOWN
Requires-Python: >3.7
Requires-Dist: click
Requires-Dist: cryptography
Requires-Dist: rich
